{"nodes": [{"id": "c_users_alex_traecoder_maids_ng_app_models_salaryschedule_php", "label": "SalarySchedule.php", "file_type": "code", "source_file": "C:\\Users\\Alex\\TraeCoder\\Maids.ng\\app\\Models\\SalarySchedule.php", "source_location": "L1"}, {"id": "models_salaryschedule_salaryschedule", "label": "SalarySchedule", "file_type": "code", "source_file": "C:\\Users\\Alex\\TraeCoder\\Maids.ng\\app\\Models\\SalarySchedule.php", "source_location": "L10"}, {"id": "models_salaryschedule_salaryschedule_assignment", "label": ".assignment()", "file_type": "code", "source_file": "C:\\Users\\Alex\\TraeCoder\\Maids.ng\\app\\Models\\SalarySchedule.php", "source_location": "L71"}, {"id": "models_salaryschedule_salaryschedule_employer", "label": ".employer()", "file_type": "code", "source_file": "C:\\Users\\Alex\\TraeCoder\\Maids.ng\\app\\Models\\SalarySchedule.php", "source_location": "L79"}, {"id": "models_salaryschedule_salaryschedule_maid", "label": ".maid()", "file_type": "code", "source_file": "C:\\Users\\Alex\\TraeCoder\\Maids.ng\\app\\Models\\SalarySchedule.php", "source_location": "L87"}, {"id": "models_salaryschedule_salaryschedule_creator", "label": ".creator()", "file_type": "code", "source_file": "C:\\Users\\Alex\\TraeCoder\\Maids.ng\\app\\Models\\SalarySchedule.php", "source_location": "L95"}, {"id": "models_salaryschedule_salaryschedule_salarypayments", "label": ".salaryPayments()", "file_type": "code", "source_file": "C:\\Users\\Alex\\TraeCoder\\Maids.ng\\app\\Models\\SalarySchedule.php", "source_location": "L103"}, {"id": "models_salaryschedule_salaryschedule_scopeactive", "label": ".scopeActive()", "file_type": "code", "source_file": "C:\\Users\\Alex\\TraeCoder\\Maids.ng\\app\\Models\\SalarySchedule.php", "source_location": "L111"}, {"id": "models_salaryschedule_salaryschedule_scopeforemployer", "label": ".scopeForEmployer()", "file_type": "code", "source_file": "C:\\Users\\Alex\\TraeCoder\\Maids.ng\\app\\Models\\SalarySchedule.php", "source_location": "L119"}, {"id": "models_salaryschedule_salaryschedule_scopeformaid", "label": ".scopeForMaid()", "file_type": "code", "source_file": "C:\\Users\\Alex\\TraeCoder\\Maids.ng\\app\\Models\\SalarySchedule.php", "source_location": "L127"}, {"id": "models_salaryschedule_salaryschedule_scopesalarydue", "label": ".scopeSalaryDue()", "file_type": "code", "source_file": "C:\\Users\\Alex\\TraeCoder\\Maids.ng\\app\\Models\\SalarySchedule.php", "source_location": "L135"}, {"id": "models_salaryschedule_salaryschedule_scopeneedsreminder", "label": ".scopeNeedsReminder()", "file_type": "code", "source_file": "C:\\Users\\Alex\\TraeCoder\\Maids.ng\\app\\Models\\SalarySchedule.php", "source_location": "L144"}, {"id": "models_salaryschedule_salaryschedule_issalaryduesoon", "label": ".isSalaryDueSoon()", "file_type": "code", "source_file": "C:\\Users\\Alex\\TraeCoder\\Maids.ng\\app\\Models\\SalarySchedule.php", "source_location": "L157"}, {"id": "models_salaryschedule_salaryschedule_shouldsendreminder", "label": ".shouldSendReminder()", "file_type": "code", "source_file": "C:\\Users\\Alex\\TraeCoder\\Maids.ng\\app\\Models\\SalarySchedule.php", "source_location": "L169"}, {"id": "models_salaryschedule_salaryschedule_calculatenextsalarydate", "label": ".calculateNextSalaryDate()", "file_type": "code", "source_file": "C:\\Users\\Alex\\TraeCoder\\Maids.ng\\app\\Models\\SalarySchedule.php", "source_location": "L188"}, {"id": "models_salaryschedule_salaryschedule_advanceperiod", "label": ".advancePeriod()", "file_type": "code", "source_file": "C:\\Users\\Alex\\TraeCoder\\Maids.ng\\app\\Models\\SalarySchedule.php", "source_location": "L204"}, {"id": "models_salaryschedule_salaryschedule_markremindersent", "label": ".markReminderSent()", "file_type": "code", "source_file": "C:\\Users\\Alex\\TraeCoder\\Maids.ng\\app\\Models\\SalarySchedule.php", "source_location": "L220"}, {"id": "models_salaryschedule_salaryschedule_fundescrow", "label": ".fundEscrow()", "file_type": "code", "source_file": "C:\\Users\\Alex\\TraeCoder\\Maids.ng\\app\\Models\\SalarySchedule.php", "source_location": "L237"}, {"id": "models_salaryschedule_salaryschedule_releaseescrowtomaid", "label": ".releaseEscrowToMaid()", "file_type": "code", "source_file": "C:\\Users\\Alex\\TraeCoder\\Maids.ng\\app\\Models\\SalarySchedule.php", "source_location": "L263"}, {"id": "models_salaryschedule_salaryschedule_escalate", "label": ".escalate()", "file_type": "code", "source_file": "C:\\Users\\Alex\\TraeCoder\\Maids.ng\\app\\Models\\SalarySchedule.php", "source_location": "L294"}, {"id": "models_salaryschedule_salaryschedule_getpaymentstatuslabelattribute", "label": ".getPaymentStatusLabelAttribute()", "file_type": "code", "source_file": "C:\\Users\\Alex\\TraeCoder\\Maids.ng\\app\\Models\\SalarySchedule.php", "source_location": "L304"}, {"id": "models_salaryschedule_salaryschedule_getdaysuntildueattribute", "label": ".getDaysUntilDueAttribute()", "file_type": "code", "source_file": "C:\\Users\\Alex\\TraeCoder\\Maids.ng\\app\\Models\\SalarySchedule.php", "source_location": "L320"}], "edges": [{"source": "c_users_alex_traecoder_maids_ng_app_models_salaryschedule_php", "target": "hasfactory", "relation": "imports", "confidence": "EXTRACTED", "source_file": "C:\\Users\\Alex\\TraeCoder\\Maids.ng\\app\\Models\\SalarySchedule.php", "source_location": "L5", "weight": 1.0}, {"source": "c_users_alex_traecoder_maids_ng_app_models_salaryschedule_php", "target": "model", "relation": "imports", "confidence": "EXTRACTED", "source_file": "C:\\Users\\Alex\\TraeCoder\\Maids.ng\\app\\Models\\SalarySchedule.php", "source_location": "L6", "weight": 1.0}, {"source": "c_users_alex_traecoder_maids_ng_app_models_salaryschedule_php", "target": "belongsto", "relation": "imports", "confidence": "EXTRACTED", "source_file": "C:\\Users\\Alex\\TraeCoder\\Maids.ng\\app\\Models\\SalarySchedule.php", "source_location": "L7", "weight": 1.0}, {"source": "c_users_alex_traecoder_maids_ng_app_models_salaryschedule_php", "target": "hasmany", "relation": "imports", "confidence": "EXTRACTED", "source_file": "C:\\Users\\Alex\\TraeCoder\\Maids.ng\\app\\Models\\SalarySchedule.php", "source_location": "L8", "weight": 1.0}, {"source": "c_users_alex_traecoder_maids_ng_app_models_salaryschedule_php", "target": "models_salaryschedule_salaryschedule", "relation": "contains", "confidence": "EXTRACTED", "source_file": "C:\\Users\\Alex\\TraeCoder\\Maids.ng\\app\\Models\\SalarySchedule.php", "source_location": "L10", "weight": 1.0}, {"source": "models_salaryschedule_salaryschedule", "target": "models_salaryschedule_salaryschedule_assignment", "relation": "method", "confidence": "EXTRACTED", "source_file": "C:\\Users\\Alex\\TraeCoder\\Maids.ng\\app\\Models\\SalarySchedule.php", "source_location": "L71", "weight": 1.0}, {"source": "models_salaryschedule_salaryschedule", "target": "models_salaryschedule_salaryschedule_employer", "relation": "method", "confidence": "EXTRACTED", "source_file": "C:\\Users\\Alex\\TraeCoder\\Maids.ng\\app\\Models\\SalarySchedule.php", "source_location": "L79", "weight": 1.0}, {"source": "models_salaryschedule_salaryschedule", "target": "models_salaryschedule_salaryschedule_maid", "relation": "method", "confidence": "EXTRACTED", "source_file": "C:\\Users\\Alex\\TraeCoder\\Maids.ng\\app\\Models\\SalarySchedule.php", "source_location": "L87", "weight": 1.0}, {"source": "models_salaryschedule_salaryschedule", "target": "models_salaryschedule_salaryschedule_creator", "relation": "method", "confidence": "EXTRACTED", "source_file": "C:\\Users\\Alex\\TraeCoder\\Maids.ng\\app\\Models\\SalarySchedule.php", "source_location": "L95", "weight": 1.0}, {"source": "models_salaryschedule_salaryschedule", "target": "models_salaryschedule_salaryschedule_salarypayments", "relation": "method", "confidence": "EXTRACTED", "source_file": "C:\\Users\\Alex\\TraeCoder\\Maids.ng\\app\\Models\\SalarySchedule.php", "source_location": "L103", "weight": 1.0}, {"source": "models_salaryschedule_salaryschedule", "target": "models_salaryschedule_salaryschedule_scopeactive", "relation": "method", "confidence": "EXTRACTED", "source_file": "C:\\Users\\Alex\\TraeCoder\\Maids.ng\\app\\Models\\SalarySchedule.php", "source_location": "L111", "weight": 1.0}, {"source": "models_salaryschedule_salaryschedule", "target": "models_salaryschedule_salaryschedule_scopeforemployer", "relation": "method", "confidence": "EXTRACTED", "source_file": "C:\\Users\\Alex\\TraeCoder\\Maids.ng\\app\\Models\\SalarySchedule.php", "source_location": "L119", "weight": 1.0}, {"source": "models_salaryschedule_salaryschedule", "target": "models_salaryschedule_salaryschedule_scopeformaid", "relation": "method", "confidence": "EXTRACTED", "source_file": "C:\\Users\\Alex\\TraeCoder\\Maids.ng\\app\\Models\\SalarySchedule.php", "source_location": "L127", "weight": 1.0}, {"source": "models_salaryschedule_salaryschedule", "target": "models_salaryschedule_salaryschedule_scopesalarydue", "relation": "method", "confidence": "EXTRACTED", "source_file": "C:\\Users\\Alex\\TraeCoder\\Maids.ng\\app\\Models\\SalarySchedule.php", "source_location": "L135", "weight": 1.0}, {"source": "models_salaryschedule_salaryschedule", "target": "models_salaryschedule_salaryschedule_scopeneedsreminder", "relation": "method", "confidence": "EXTRACTED", "source_file": "C:\\Users\\Alex\\TraeCoder\\Maids.ng\\app\\Models\\SalarySchedule.php", "source_location": "L144", "weight": 1.0}, {"source": "models_salaryschedule_salaryschedule", "target": "models_salaryschedule_salaryschedule_issalaryduesoon", "relation": "method", "confidence": "EXTRACTED", "source_file": "C:\\Users\\Alex\\TraeCoder\\Maids.ng\\app\\Models\\SalarySchedule.php", "source_location": "L157", "weight": 1.0}, {"source": "models_salaryschedule_salaryschedule", "target": "models_salaryschedule_salaryschedule_shouldsendreminder", "relation": "method", "confidence": "EXTRACTED", "source_file": "C:\\Users\\Alex\\TraeCoder\\Maids.ng\\app\\Models\\SalarySchedule.php", "source_location": "L169", "weight": 1.0}, {"source": "models_salaryschedule_salaryschedule", "target": "models_salaryschedule_salaryschedule_calculatenextsalarydate", "relation": "method", "confidence": "EXTRACTED", "source_file": "C:\\Users\\Alex\\TraeCoder\\Maids.ng\\app\\Models\\SalarySchedule.php", "source_location": "L188", "weight": 1.0}, {"source": "models_salaryschedule_salaryschedule", "target": "models_salaryschedule_salaryschedule_advanceperiod", "relation": "method", "confidence": "EXTRACTED", "source_file": "C:\\Users\\Alex\\TraeCoder\\Maids.ng\\app\\Models\\SalarySchedule.php", "source_location": "L204", "weight": 1.0}, {"source": "models_salaryschedule_salaryschedule", "target": "models_salaryschedule_salaryschedule_markremindersent", "relation": "method", "confidence": "EXTRACTED", "source_file": "C:\\Users\\Alex\\TraeCoder\\Maids.ng\\app\\Models\\SalarySchedule.php", "source_location": "L220", "weight": 1.0}, {"source": "models_salaryschedule_salaryschedule", "target": "models_salaryschedule_salaryschedule_fundescrow", "relation": "method", "confidence": "EXTRACTED", "source_file": "C:\\Users\\Alex\\TraeCoder\\Maids.ng\\app\\Models\\SalarySchedule.php", "source_location": "L237", "weight": 1.0}, {"source": "models_salaryschedule_salaryschedule", "target": "models_salaryschedule_salaryschedule_releaseescrowtomaid", "relation": "method", "confidence": "EXTRACTED", "source_file": "C:\\Users\\Alex\\TraeCoder\\Maids.ng\\app\\Models\\SalarySchedule.php", "source_location": "L263", "weight": 1.0}, {"source": "models_salaryschedule_salaryschedule", "target": "models_salaryschedule_salaryschedule_escalate", "relation": "method", "confidence": "EXTRACTED", "source_file": "C:\\Users\\Alex\\TraeCoder\\Maids.ng\\app\\Models\\SalarySchedule.php", "source_location": "L294", "weight": 1.0}, {"source": "models_salaryschedule_salaryschedule", "target": "models_salaryschedule_salaryschedule_getpaymentstatuslabelattribute", "relation": "method", "confidence": "EXTRACTED", "source_file": "C:\\Users\\Alex\\TraeCoder\\Maids.ng\\app\\Models\\SalarySchedule.php", "source_location": "L304", "weight": 1.0}, {"source": "models_salaryschedule_salaryschedule", "target": "models_salaryschedule_salaryschedule_getdaysuntildueattribute", "relation": "method", "confidence": "EXTRACTED", "source_file": "C:\\Users\\Alex\\TraeCoder\\Maids.ng\\app\\Models\\SalarySchedule.php", "source_location": "L320", "weight": 1.0}, {"source": "models_salaryschedule_salaryschedule_advanceperiod", "target": "models_salaryschedule_salaryschedule_calculatenextsalarydate", "relation": "calls", "confidence": "EXTRACTED", "source_file": "C:\\Users\\Alex\\TraeCoder\\Maids.ng\\app\\Models\\SalarySchedule.php", "source_location": "L208", "weight": 1.0}], "raw_calls": [{"caller_nid": "models_salaryschedule_salaryschedule_assignment", "callee": "belongsTo", "is_member_call": true, "source_file": "C:\\Users\\Alex\\TraeCoder\\Maids.ng\\app\\Models\\SalarySchedule.php", "source_location": "L73"}, {"caller_nid": "models_salaryschedule_salaryschedule_employer", "callee": "belongsTo", "is_member_call": true, "source_file": "C:\\Users\\Alex\\TraeCoder\\Maids.ng\\app\\Models\\SalarySchedule.php", "source_location": "L81"}, {"caller_nid": "models_salaryschedule_salaryschedule_maid", "callee": "belongsTo", "is_member_call": true, "source_file": "C:\\Users\\Alex\\TraeCoder\\Maids.ng\\app\\Models\\SalarySchedule.php", "source_location": "L89"}, {"caller_nid": "models_salaryschedule_salaryschedule_creator", "callee": "belongsTo", "is_member_call": true, "source_file": "C:\\Users\\Alex\\TraeCoder\\Maids.ng\\app\\Models\\SalarySchedule.php", "source_location": "L97"}, {"caller_nid": "models_salaryschedule_salaryschedule_salarypayments", "callee": "hasMany", "is_member_call": true, "source_file": "C:\\Users\\Alex\\TraeCoder\\Maids.ng\\app\\Models\\SalarySchedule.php", "source_location": "L105"}, {"caller_nid": "models_salaryschedule_salaryschedule_scopeactive", "callee": "where", "is_member_call": true, "source_file": "C:\\Users\\Alex\\TraeCoder\\Maids.ng\\app\\Models\\SalarySchedule.php", "source_location": "L113"}, {"caller_nid": "models_salaryschedule_salaryschedule_scopeforemployer", "callee": "where", "is_member_call": true, "source_file": "C:\\Users\\Alex\\TraeCoder\\Maids.ng\\app\\Models\\SalarySchedule.php", "source_location": "L121"}, {"caller_nid": "models_salaryschedule_salaryschedule_scopeformaid", "callee": "where", "is_member_call": true, "source_file": "C:\\Users\\Alex\\TraeCoder\\Maids.ng\\app\\Models\\SalarySchedule.php", "source_location": "L129"}, {"caller_nid": "models_salaryschedule_salaryschedule_scopesalarydue", "callee": "where", "is_member_call": true, "source_file": "C:\\Users\\Alex\\TraeCoder\\Maids.ng\\app\\Models\\SalarySchedule.php", "source_location": "L137"}, {"caller_nid": "models_salaryschedule_salaryschedule_scopesalarydue", "callee": "where", "is_member_call": true, "source_file": "C:\\Users\\Alex\\TraeCoder\\Maids.ng\\app\\Models\\SalarySchedule.php", "source_location": "L137"}, {"caller_nid": "models_salaryschedule_salaryschedule_scopesalarydue", "callee": "addDays", "is_member_call": true, "source_file": "C:\\Users\\Alex\\TraeCoder\\Maids.ng\\app\\Models\\SalarySchedule.php", "source_location": "L137"}, {"caller_nid": "models_salaryschedule_salaryschedule_scopesalarydue", "callee": "now", "is_member_call": false, "source_file": "C:\\Users\\Alex\\TraeCoder\\Maids.ng\\app\\Models\\SalarySchedule.php", "source_location": "L137"}, {"caller_nid": "models_salaryschedule_salaryschedule_scopeneedsreminder", "callee": "where", "is_member_call": true, "source_file": "C:\\Users\\Alex\\TraeCoder\\Maids.ng\\app\\Models\\SalarySchedule.php", "source_location": "L146"}, {"caller_nid": "models_salaryschedule_salaryschedule_scopeneedsreminder", "callee": "where", "is_member_call": true, "source_file": "C:\\Users\\Alex\\TraeCoder\\Maids.ng\\app\\Models\\SalarySchedule.php", "source_location": "L146"}, {"caller_nid": "models_salaryschedule_salaryschedule_scopeneedsreminder", "callee": "where", "is_member_call": true, "source_file": "C:\\Users\\Alex\\TraeCoder\\Maids.ng\\app\\Models\\SalarySchedule.php", "source_location": "L146"}, {"caller_nid": "models_salaryschedule_salaryschedule_scopeneedsreminder", "callee": "orWhere", "is_member_call": true, "source_file": "C:\\Users\\Alex\\TraeCoder\\Maids.ng\\app\\Models\\SalarySchedule.php", "source_location": "L149"}, {"caller_nid": "models_salaryschedule_salaryschedule_scopeneedsreminder", "callee": "whereNull", "is_member_call": true, "source_file": "C:\\Users\\Alex\\TraeCoder\\Maids.ng\\app\\Models\\SalarySchedule.php", "source_location": "L149"}, {"caller_nid": "models_salaryschedule_salaryschedule_scopeneedsreminder", "callee": "now", "is_member_call": false, "source_file": "C:\\Users\\Alex\\TraeCoder\\Maids.ng\\app\\Models\\SalarySchedule.php", "source_location": "L150"}, {"caller_nid": "models_salaryschedule_salaryschedule_issalaryduesoon", "callee": "diffInDays", "is_member_call": true, "source_file": "C:\\Users\\Alex\\TraeCoder\\Maids.ng\\app\\Models\\SalarySchedule.php", "source_location": "L163"}, {"caller_nid": "models_salaryschedule_salaryschedule_issalaryduesoon", "callee": "now", "is_member_call": false, "source_file": "C:\\Users\\Alex\\TraeCoder\\Maids.ng\\app\\Models\\SalarySchedule.php", "source_location": "L163"}, {"caller_nid": "models_salaryschedule_salaryschedule_shouldsendreminder", "callee": "subDays", "is_member_call": true, "source_file": "C:\\Users\\Alex\\TraeCoder\\Maids.ng\\app\\Models\\SalarySchedule.php", "source_location": "L179"}, {"caller_nid": "models_salaryschedule_salaryschedule_shouldsendreminder", "callee": "copy", "is_member_call": true, "source_file": "C:\\Users\\Alex\\TraeCoder\\Maids.ng\\app\\Models\\SalarySchedule.php", "source_location": "L179"}, {"caller_nid": "models_salaryschedule_salaryschedule_shouldsendreminder", "callee": "gte", "is_member_call": true, "source_file": "C:\\Users\\Alex\\TraeCoder\\Maids.ng\\app\\Models\\SalarySchedule.php", "source_location": "L181"}, {"caller_nid": "models_salaryschedule_salaryschedule_shouldsendreminder", "callee": "now", "is_member_call": false, "source_file": "C:\\Users\\Alex\\TraeCoder\\Maids.ng\\app\\Models\\SalarySchedule.php", "source_location": "L181"}, {"caller_nid": "models_salaryschedule_salaryschedule_shouldsendreminder", "callee": "gte", "is_member_call": true, "source_file": "C:\\Users\\Alex\\TraeCoder\\Maids.ng\\app\\Models\\SalarySchedule.php", "source_location": "L182"}, {"caller_nid": "models_salaryschedule_salaryschedule_shouldsendreminder", "callee": "now", "is_member_call": false, "source_file": "C:\\Users\\Alex\\TraeCoder\\Maids.ng\\app\\Models\\SalarySchedule.php", "source_location": "L182"}, {"caller_nid": "models_salaryschedule_salaryschedule_calculatenextsalarydate", "callee": "now", "is_member_call": false, "source_file": "C:\\Users\\Alex\\TraeCoder\\Maids.ng\\app\\Models\\SalarySchedule.php", "source_location": "L190"}, {"caller_nid": "models_salaryschedule_salaryschedule_calculatenextsalarydate", "callee": "setDay", "is_member_call": true, "source_file": "C:\\Users\\Alex\\TraeCoder\\Maids.ng\\app\\Models\\SalarySchedule.php", "source_location": "L191"}, {"caller_nid": "models_salaryschedule_salaryschedule_calculatenextsalarydate", "callee": "copy", "is_member_call": true, "source_file": "C:\\Users\\Alex\\TraeCoder\\Maids.ng\\app\\Models\\SalarySchedule.php", "source_location": "L191"}, {"caller_nid": "models_salaryschedule_salaryschedule_calculatenextsalarydate", "callee": "isPast", "is_member_call": true, "source_file": "C:\\Users\\Alex\\TraeCoder\\Maids.ng\\app\\Models\\SalarySchedule.php", "source_location": "L194"}, {"caller_nid": "models_salaryschedule_salaryschedule_calculatenextsalarydate", "callee": "isToday", "is_member_call": true, "source_file": "C:\\Users\\Alex\\TraeCoder\\Maids.ng\\app\\Models\\SalarySchedule.php", "source_location": "L194"}, {"caller_nid": "models_salaryschedule_salaryschedule_calculatenextsalarydate", "callee": "addMonth", "is_member_call": true, "source_file": "C:\\Users\\Alex\\TraeCoder\\Maids.ng\\app\\Models\\SalarySchedule.php", "source_location": "L195"}, {"caller_nid": "models_salaryschedule_salaryschedule_advanceperiod", "callee": "addDay", "is_member_call": true, "source_file": "C:\\Users\\Alex\\TraeCoder\\Maids.ng\\app\\Models\\SalarySchedule.php", "source_location": "L207"}, {"caller_nid": "models_salaryschedule_salaryschedule_advanceperiod", "callee": "copy", "is_member_call": true, "source_file": "C:\\Users\\Alex\\TraeCoder\\Maids.ng\\app\\Models\\SalarySchedule.php", "source_location": "L207"}, {"caller_nid": "models_salaryschedule_salaryschedule_advanceperiod", "callee": "save", "is_member_call": true, "source_file": "C:\\Users\\Alex\\TraeCoder\\Maids.ng\\app\\Models\\SalarySchedule.php", "source_location": "L214"}, {"caller_nid": "models_salaryschedule_salaryschedule_markremindersent", "callee": "now", "is_member_call": false, "source_file": "C:\\Users\\Alex\\TraeCoder\\Maids.ng\\app\\Models\\SalarySchedule.php", "source_location": "L223"}, {"caller_nid": "models_salaryschedule_salaryschedule_markremindersent", "callee": "addDays", "is_member_call": true, "source_file": "C:\\Users\\Alex\\TraeCoder\\Maids.ng\\app\\Models\\SalarySchedule.php", "source_location": "L227"}, {"caller_nid": "models_salaryschedule_salaryschedule_markremindersent", "callee": "now", "is_member_call": false, "source_file": "C:\\Users\\Alex\\TraeCoder\\Maids.ng\\app\\Models\\SalarySchedule.php", "source_location": "L227"}, {"caller_nid": "models_salaryschedule_salaryschedule_markremindersent", "callee": "save", "is_member_call": true, "source_file": "C:\\Users\\Alex\\TraeCoder\\Maids.ng\\app\\Models\\SalarySchedule.php", "source_location": "L231"}, {"caller_nid": "models_salaryschedule_salaryschedule_fundescrow", "callee": "first", "is_member_call": true, "source_file": "C:\\Users\\Alex\\TraeCoder\\Maids.ng\\app\\Models\\SalarySchedule.php", "source_location": "L239"}, {"caller_nid": "models_salaryschedule_salaryschedule_fundescrow", "callee": "EmployerWallet", "is_member_call": false, "source_file": "C:\\Users\\Alex\\TraeCoder\\Maids.ng\\app\\Models\\SalarySchedule.php", "source_location": "L239"}, {"caller_nid": "models_salaryschedule_salaryschedule_fundescrow", "callee": "hasSufficientBalance", "is_member_call": true, "source_file": "C:\\Users\\Alex\\TraeCoder\\Maids.ng\\app\\Models\\SalarySchedule.php", "source_location": "L241"}, {"caller_nid": "models_salaryschedule_salaryschedule_fundescrow", "callee": "holdInEscrow", "is_member_call": true, "source_file": "C:\\Users\\Alex\\TraeCoder\\Maids.ng\\app\\Models\\SalarySchedule.php", "source_location": "L245"}, {"caller_nid": "models_salaryschedule_salaryschedule_fundescrow", "callee": "now", "is_member_call": false, "source_file": "C:\\Users\\Alex\\TraeCoder\\Maids.ng\\app\\Models\\SalarySchedule.php", "source_location": "L253"}, {"caller_nid": "models_salaryschedule_salaryschedule_fundescrow", "callee": "save", "is_member_call": true, "source_file": "C:\\Users\\Alex\\TraeCoder\\Maids.ng\\app\\Models\\SalarySchedule.php", "source_location": "L255"}, {"caller_nid": "models_salaryschedule_salaryschedule_releaseescrowtomaid", "callee": "first", "is_member_call": true, "source_file": "C:\\Users\\Alex\\TraeCoder\\Maids.ng\\app\\Models\\SalarySchedule.php", "source_location": "L269"}, {"caller_nid": "models_salaryschedule_salaryschedule_releaseescrowtomaid", "callee": "EmployerWallet", "is_member_call": false, "source_file": "C:\\Users\\Alex\\TraeCoder\\Maids.ng\\app\\Models\\SalarySchedule.php", "source_location": "L269"}, {"caller_nid": "models_salaryschedule_salaryschedule_releaseescrowtomaid", "callee": "save", "is_member_call": true, "source_file": "C:\\Users\\Alex\\TraeCoder\\Maids.ng\\app\\Models\\SalarySchedule.php", "source_location": "L285"}, {"caller_nid": "models_salaryschedule_salaryschedule_escalate", "callee": "now", "is_member_call": false, "source_file": "C:\\Users\\Alex\\TraeCoder\\Maids.ng\\app\\Models\\SalarySchedule.php", "source_location": "L297"}, {"caller_nid": "models_salaryschedule_salaryschedule_escalate", "callee": "save", "is_member_call": true, "source_file": "C:\\Users\\Alex\\TraeCoder\\Maids.ng\\app\\Models\\SalarySchedule.php", "source_location": "L298"}, {"caller_nid": "models_salaryschedule_salaryschedule_getpaymentstatuslabelattribute", "callee": "ucfirst", "is_member_call": false, "source_file": "C:\\Users\\Alex\\TraeCoder\\Maids.ng\\app\\Models\\SalarySchedule.php", "source_location": "L313"}, {"caller_nid": "models_salaryschedule_salaryschedule_getdaysuntildueattribute", "callee": "diffInDays", "is_member_call": true, "source_file": "C:\\Users\\Alex\\TraeCoder\\Maids.ng\\app\\Models\\SalarySchedule.php", "source_location": "L326"}, {"caller_nid": "models_salaryschedule_salaryschedule_getdaysuntildueattribute", "callee": "now", "is_member_call": false, "source_file": "C:\\Users\\Alex\\TraeCoder\\Maids.ng\\app\\Models\\SalarySchedule.php", "source_location": "L326"}]}