{"nodes": [{"id": "c_users_alex_traecoder_maids_ng_legacy_v1_vendor_inertiajs_inertia_laravel_src_middleware_php", "label": "Middleware.php", "file_type": "code", "source_file": "C:\\Users\\Alex\\TraeCoder\\Maids.ng\\legacy-v1\\vendor\\inertiajs\\inertia-laravel\\src\\Middleware.php", "source_location": "L1"}, {"id": "src_middleware_middleware", "label": "Middleware", "file_type": "code", "source_file": "C:\\Users\\Alex\\TraeCoder\\Maids.ng\\legacy-v1\\vendor\\inertiajs\\inertia-laravel\\src\\Middleware.php", "source_location": "L16"}, {"id": "src_middleware_middleware_version", "label": ".version()", "file_type": "code", "source_file": "C:\\Users\\Alex\\TraeCoder\\Maids.ng\\legacy-v1\\vendor\\inertiajs\\inertia-laravel\\src\\Middleware.php", "source_location": "L46"}, {"id": "src_middleware_middleware_share", "label": ".share()", "file_type": "code", "source_file": "C:\\Users\\Alex\\TraeCoder\\Maids.ng\\legacy-v1\\vendor\\inertiajs\\inertia-laravel\\src\\Middleware.php", "source_location": "L68"}, {"id": "src_middleware_middleware_shareonce", "label": ".shareOnce()", "file_type": "code", "source_file": "C:\\Users\\Alex\\TraeCoder\\Maids.ng\\legacy-v1\\vendor\\inertiajs\\inertia-laravel\\src\\Middleware.php", "source_location": "L80"}, {"id": "src_middleware_middleware_rootview", "label": ".rootView()", "file_type": "code", "source_file": "C:\\Users\\Alex\\TraeCoder\\Maids.ng\\legacy-v1\\vendor\\inertiajs\\inertia-laravel\\src\\Middleware.php", "source_location": "L90"}, {"id": "src_middleware_middleware_urlresolver", "label": ".urlResolver()", "file_type": "code", "source_file": "C:\\Users\\Alex\\TraeCoder\\Maids.ng\\legacy-v1\\vendor\\inertiajs\\inertia-laravel\\src\\Middleware.php", "source_location": "L100"}, {"id": "src_middleware_middleware_handle", "label": ".handle()", "file_type": "code", "source_file": "C:\\Users\\Alex\\TraeCoder\\Maids.ng\\legacy-v1\\vendor\\inertiajs\\inertia-laravel\\src\\Middleware.php", "source_location": "L110"}, {"id": "src_middleware_middleware_redirecthasfragment", "label": ".redirectHasFragment()", "file_type": "code", "source_file": "C:\\Users\\Alex\\TraeCoder\\Maids.ng\\legacy-v1\\vendor\\inertiajs\\inertia-laravel\\src\\Middleware.php", "source_location": "L171"}, {"id": "src_middleware_middleware_reflash", "label": ".reflash()", "file_type": "code", "source_file": "C:\\Users\\Alex\\TraeCoder\\Maids.ng\\legacy-v1\\vendor\\inertiajs\\inertia-laravel\\src\\Middleware.php", "source_location": "L179"}, {"id": "src_middleware_middleware_onemptyresponse", "label": ".onEmptyResponse()", "file_type": "code", "source_file": "C:\\Users\\Alex\\TraeCoder\\Maids.ng\\legacy-v1\\vendor\\inertiajs\\inertia-laravel\\src\\Middleware.php", "source_location": "L189"}, {"id": "src_middleware_middleware_onredirectwithfragment", "label": ".onRedirectWithFragment()", "file_type": "code", "source_file": "C:\\Users\\Alex\\TraeCoder\\Maids.ng\\legacy-v1\\vendor\\inertiajs\\inertia-laravel\\src\\Middleware.php", "source_location": "L197"}, {"id": "src_middleware_middleware_onversionchange", "label": ".onVersionChange()", "file_type": "code", "source_file": "C:\\Users\\Alex\\TraeCoder\\Maids.ng\\legacy-v1\\vendor\\inertiajs\\inertia-laravel\\src\\Middleware.php", "source_location": "L207"}, {"id": "src_middleware_middleware_resolvevalidationerrors", "label": ".resolveValidationErrors()", "file_type": "code", "source_file": "C:\\Users\\Alex\\TraeCoder\\Maids.ng\\legacy-v1\\vendor\\inertiajs\\inertia-laravel\\src\\Middleware.php", "source_location": "L223"}], "edges": [{"source": "c_users_alex_traecoder_maids_ng_legacy_v1_vendor_inertiajs_inertia_laravel_src_middleware_php", "target": "closure", "relation": "imports", "confidence": "EXTRACTED", "source_file": "C:\\Users\\Alex\\TraeCoder\\Maids.ng\\legacy-v1\\vendor\\inertiajs\\inertia-laravel\\src\\Middleware.php", "source_location": "L5", "weight": 1.0}, {"source": "c_users_alex_traecoder_maids_ng_legacy_v1_vendor_inertiajs_inertia_laravel_src_middleware_php", "target": "request", "relation": "imports", "confidence": "EXTRACTED", "source_file": "C:\\Users\\Alex\\TraeCoder\\Maids.ng\\legacy-v1\\vendor\\inertiajs\\inertia-laravel\\src\\Middleware.php", "source_location": "L6", "weight": 1.0}, {"source": "c_users_alex_traecoder_maids_ng_legacy_v1_vendor_inertiajs_inertia_laravel_src_middleware_php", "target": "store", "relation": "imports", "confidence": "EXTRACTED", "source_file": "C:\\Users\\Alex\\TraeCoder\\Maids.ng\\legacy-v1\\vendor\\inertiajs\\inertia-laravel\\src\\Middleware.php", "source_location": "L7", "weight": 1.0}, {"source": "c_users_alex_traecoder_maids_ng_legacy_v1_vendor_inertiajs_inertia_laravel_src_middleware_php", "target": "redirect", "relation": "imports", "confidence": "EXTRACTED", "source_file": "C:\\Users\\Alex\\TraeCoder\\Maids.ng\\legacy-v1\\vendor\\inertiajs\\inertia-laravel\\src\\Middleware.php", "source_location": "L8", "weight": 1.0}, {"source": "c_users_alex_traecoder_maids_ng_legacy_v1_vendor_inertiajs_inertia_laravel_src_middleware_php", "target": "messagebag", "relation": "imports", "confidence": "EXTRACTED", "source_file": "C:\\Users\\Alex\\TraeCoder\\Maids.ng\\legacy-v1\\vendor\\inertiajs\\inertia-laravel\\src\\Middleware.php", "source_location": "L9", "weight": 1.0}, {"source": "c_users_alex_traecoder_maids_ng_legacy_v1_vendor_inertiajs_inertia_laravel_src_middleware_php", "target": "excludesssrpaths", "relation": "imports", "confidence": "EXTRACTED", "source_file": "C:\\Users\\Alex\\TraeCoder\\Maids.ng\\legacy-v1\\vendor\\inertiajs\\inertia-laravel\\src\\Middleware.php", "source_location": "L10", "weight": 1.0}, {"source": "c_users_alex_traecoder_maids_ng_legacy_v1_vendor_inertiajs_inertia_laravel_src_middleware_php", "target": "gateway", "relation": "imports", "confidence": "EXTRACTED", "source_file": "C:\\Users\\Alex\\TraeCoder\\Maids.ng\\legacy-v1\\vendor\\inertiajs\\inertia-laravel\\src\\Middleware.php", "source_location": "L11", "weight": 1.0}, {"source": "c_users_alex_traecoder_maids_ng_legacy_v1_vendor_inertiajs_inertia_laravel_src_middleware_php", "target": "header", "relation": "imports", "confidence": "EXTRACTED", "source_file": "C:\\Users\\Alex\\TraeCoder\\Maids.ng\\legacy-v1\\vendor\\inertiajs\\inertia-laravel\\src\\Middleware.php", "source_location": "L12", "weight": 1.0}, {"source": "c_users_alex_traecoder_maids_ng_legacy_v1_vendor_inertiajs_inertia_laravel_src_middleware_php", "target": "sessionkey", "relation": "imports", "confidence": "EXTRACTED", "source_file": "C:\\Users\\Alex\\TraeCoder\\Maids.ng\\legacy-v1\\vendor\\inertiajs\\inertia-laravel\\src\\Middleware.php", "source_location": "L13", "weight": 1.0}, {"source": "c_users_alex_traecoder_maids_ng_legacy_v1_vendor_inertiajs_inertia_laravel_src_middleware_php", "target": "response", "relation": "imports", "confidence": "EXTRACTED", "source_file": "C:\\Users\\Alex\\TraeCoder\\Maids.ng\\legacy-v1\\vendor\\inertiajs\\inertia-laravel\\src\\Middleware.php", "source_location": "L14", "weight": 1.0}, {"source": "c_users_alex_traecoder_maids_ng_legacy_v1_vendor_inertiajs_inertia_laravel_src_middleware_php", "target": "src_middleware_middleware", "relation": "contains", "confidence": "EXTRACTED", "source_file": "C:\\Users\\Alex\\TraeCoder\\Maids.ng\\legacy-v1\\vendor\\inertiajs\\inertia-laravel\\src\\Middleware.php", "source_location": "L16", "weight": 1.0}, {"source": "src_middleware_middleware", "target": "src_middleware_middleware_version", "relation": "method", "confidence": "EXTRACTED", "source_file": "C:\\Users\\Alex\\TraeCoder\\Maids.ng\\legacy-v1\\vendor\\inertiajs\\inertia-laravel\\src\\Middleware.php", "source_location": "L46", "weight": 1.0}, {"source": "src_middleware_middleware", "target": "src_middleware_middleware_share", "relation": "method", "confidence": "EXTRACTED", "source_file": "C:\\Users\\Alex\\TraeCoder\\Maids.ng\\legacy-v1\\vendor\\inertiajs\\inertia-laravel\\src\\Middleware.php", "source_location": "L68", "weight": 1.0}, {"source": "src_middleware_middleware", "target": "src_middleware_middleware_shareonce", "relation": "method", "confidence": "EXTRACTED", "source_file": "C:\\Users\\Alex\\TraeCoder\\Maids.ng\\legacy-v1\\vendor\\inertiajs\\inertia-laravel\\src\\Middleware.php", "source_location": "L80", "weight": 1.0}, {"source": "src_middleware_middleware", "target": "src_middleware_middleware_rootview", "relation": "method", "confidence": "EXTRACTED", "source_file": "C:\\Users\\Alex\\TraeCoder\\Maids.ng\\legacy-v1\\vendor\\inertiajs\\inertia-laravel\\src\\Middleware.php", "source_location": "L90", "weight": 1.0}, {"source": "src_middleware_middleware", "target": "src_middleware_middleware_urlresolver", "relation": "method", "confidence": "EXTRACTED", "source_file": "C:\\Users\\Alex\\TraeCoder\\Maids.ng\\legacy-v1\\vendor\\inertiajs\\inertia-laravel\\src\\Middleware.php", "source_location": "L100", "weight": 1.0}, {"source": "src_middleware_middleware", "target": "src_middleware_middleware_handle", "relation": "method", "confidence": "EXTRACTED", "source_file": "C:\\Users\\Alex\\TraeCoder\\Maids.ng\\legacy-v1\\vendor\\inertiajs\\inertia-laravel\\src\\Middleware.php", "source_location": "L110", "weight": 1.0}, {"source": "src_middleware_middleware", "target": "src_middleware_middleware_redirecthasfragment", "relation": "method", "confidence": "EXTRACTED", "source_file": "C:\\Users\\Alex\\TraeCoder\\Maids.ng\\legacy-v1\\vendor\\inertiajs\\inertia-laravel\\src\\Middleware.php", "source_location": "L171", "weight": 1.0}, {"source": "src_middleware_middleware", "target": "src_middleware_middleware_reflash", "relation": "method", "confidence": "EXTRACTED", "source_file": "C:\\Users\\Alex\\TraeCoder\\Maids.ng\\legacy-v1\\vendor\\inertiajs\\inertia-laravel\\src\\Middleware.php", "source_location": "L179", "weight": 1.0}, {"source": "src_middleware_middleware", "target": "src_middleware_middleware_onemptyresponse", "relation": "method", "confidence": "EXTRACTED", "source_file": "C:\\Users\\Alex\\TraeCoder\\Maids.ng\\legacy-v1\\vendor\\inertiajs\\inertia-laravel\\src\\Middleware.php", "source_location": "L189", "weight": 1.0}, {"source": "src_middleware_middleware", "target": "src_middleware_middleware_onredirectwithfragment", "relation": "method", "confidence": "EXTRACTED", "source_file": "C:\\Users\\Alex\\TraeCoder\\Maids.ng\\legacy-v1\\vendor\\inertiajs\\inertia-laravel\\src\\Middleware.php", "source_location": "L197", "weight": 1.0}, {"source": "src_middleware_middleware", "target": "src_middleware_middleware_onversionchange", "relation": "method", "confidence": "EXTRACTED", "source_file": "C:\\Users\\Alex\\TraeCoder\\Maids.ng\\legacy-v1\\vendor\\inertiajs\\inertia-laravel\\src\\Middleware.php", "source_location": "L207", "weight": 1.0}, {"source": "src_middleware_middleware", "target": "src_middleware_middleware_resolvevalidationerrors", "relation": "method", "confidence": "EXTRACTED", "source_file": "C:\\Users\\Alex\\TraeCoder\\Maids.ng\\legacy-v1\\vendor\\inertiajs\\inertia-laravel\\src\\Middleware.php", "source_location": "L223", "weight": 1.0}, {"source": "src_middleware_middleware_share", "target": "src_middleware_middleware_resolvevalidationerrors", "relation": "calls", "confidence": "EXTRACTED", "source_file": "C:\\Users\\Alex\\TraeCoder\\Maids.ng\\legacy-v1\\vendor\\inertiajs\\inertia-laravel\\src\\Middleware.php", "source_location": "L71", "weight": 1.0}, {"source": "src_middleware_middleware_handle", "target": "src_middleware_middleware_version", "relation": "calls", "confidence": "EXTRACTED", "source_file": "C:\\Users\\Alex\\TraeCoder\\Maids.ng\\legacy-v1\\vendor\\inertiajs\\inertia-laravel\\src\\Middleware.php", "source_location": "L113", "weight": 1.0}, {"source": "src_middleware_middleware_handle", "target": "src_middleware_middleware_share", "relation": "calls", "confidence": "EXTRACTED", "source_file": "C:\\Users\\Alex\\TraeCoder\\Maids.ng\\legacy-v1\\vendor\\inertiajs\\inertia-laravel\\src\\Middleware.php", "source_location": "L116", "weight": 1.0}, {"source": "src_middleware_middleware_handle", "target": "src_middleware_middleware_shareonce", "relation": "calls", "confidence": "EXTRACTED", "source_file": "C:\\Users\\Alex\\TraeCoder\\Maids.ng\\legacy-v1\\vendor\\inertiajs\\inertia-laravel\\src\\Middleware.php", "source_location": "L118", "weight": 1.0}, {"source": "src_middleware_middleware_handle", "target": "src_middleware_middleware_rootview", "relation": "calls", "confidence": "EXTRACTED", "source_file": "C:\\Users\\Alex\\TraeCoder\\Maids.ng\\legacy-v1\\vendor\\inertiajs\\inertia-laravel\\src\\Middleware.php", "source_location": "L126", "weight": 1.0}, {"source": "src_middleware_middleware_handle", "target": "src_middleware_middleware_urlresolver", "relation": "calls", "confidence": "EXTRACTED", "source_file": "C:\\Users\\Alex\\TraeCoder\\Maids.ng\\legacy-v1\\vendor\\inertiajs\\inertia-laravel\\src\\Middleware.php", "source_location": "L128", "weight": 1.0}, {"source": "src_middleware_middleware_handle", "target": "src_middleware_middleware_reflash", "relation": "calls", "confidence": "EXTRACTED", "source_file": "C:\\Users\\Alex\\TraeCoder\\Maids.ng\\legacy-v1\\vendor\\inertiajs\\inertia-laravel\\src\\Middleware.php", "source_location": "L142", "weight": 1.0}, {"source": "src_middleware_middleware_handle", "target": "src_middleware_middleware_onversionchange", "relation": "calls", "confidence": "EXTRACTED", "source_file": "C:\\Users\\Alex\\TraeCoder\\Maids.ng\\legacy-v1\\vendor\\inertiajs\\inertia-laravel\\src\\Middleware.php", "source_location": "L150", "weight": 1.0}, {"source": "src_middleware_middleware_handle", "target": "src_middleware_middleware_onemptyresponse", "relation": "calls", "confidence": "EXTRACTED", "source_file": "C:\\Users\\Alex\\TraeCoder\\Maids.ng\\legacy-v1\\vendor\\inertiajs\\inertia-laravel\\src\\Middleware.php", "source_location": "L154", "weight": 1.0}, {"source": "src_middleware_middleware_handle", "target": "src_middleware_middleware_redirecthasfragment", "relation": "calls", "confidence": "EXTRACTED", "source_file": "C:\\Users\\Alex\\TraeCoder\\Maids.ng\\legacy-v1\\vendor\\inertiajs\\inertia-laravel\\src\\Middleware.php", "source_location": "L161", "weight": 1.0}, {"source": "src_middleware_middleware_handle", "target": "src_middleware_middleware_onredirectwithfragment", "relation": "calls", "confidence": "EXTRACTED", "source_file": "C:\\Users\\Alex\\TraeCoder\\Maids.ng\\legacy-v1\\vendor\\inertiajs\\inertia-laravel\\src\\Middleware.php", "source_location": "L162", "weight": 1.0}, {"source": "src_middleware_middleware_onversionchange", "target": "src_middleware_middleware_reflash", "relation": "calls", "confidence": "EXTRACTED", "source_file": "C:\\Users\\Alex\\TraeCoder\\Maids.ng\\legacy-v1\\vendor\\inertiajs\\inertia-laravel\\src\\Middleware.php", "source_location": "L212", "weight": 1.0}], "raw_calls": [{"caller_nid": "src_middleware_middleware_version", "callee": "config", "is_member_call": false, "source_file": "C:\\Users\\Alex\\TraeCoder\\Maids.ng\\legacy-v1\\vendor\\inertiajs\\inertia-laravel\\src\\Middleware.php", "source_location": "L48"}, {"caller_nid": "src_middleware_middleware_version", "callee": "hash", "is_member_call": false, "source_file": "C:\\Users\\Alex\\TraeCoder\\Maids.ng\\legacy-v1\\vendor\\inertiajs\\inertia-laravel\\src\\Middleware.php", "source_location": "L49"}, {"caller_nid": "src_middleware_middleware_version", "callee": "config", "is_member_call": false, "source_file": "C:\\Users\\Alex\\TraeCoder\\Maids.ng\\legacy-v1\\vendor\\inertiajs\\inertia-laravel\\src\\Middleware.php", "source_location": "L49"}, {"caller_nid": "src_middleware_middleware_version", "callee": "file_exists", "is_member_call": false, "source_file": "C:\\Users\\Alex\\TraeCoder\\Maids.ng\\legacy-v1\\vendor\\inertiajs\\inertia-laravel\\src\\Middleware.php", "source_location": "L52"}, {"caller_nid": "src_middleware_middleware_version", "callee": "public_path", "is_member_call": false, "source_file": "C:\\Users\\Alex\\TraeCoder\\Maids.ng\\legacy-v1\\vendor\\inertiajs\\inertia-laravel\\src\\Middleware.php", "source_location": "L52"}, {"caller_nid": "src_middleware_middleware_version", "callee": "hash_file", "is_member_call": false, "source_file": "C:\\Users\\Alex\\TraeCoder\\Maids.ng\\legacy-v1\\vendor\\inertiajs\\inertia-laravel\\src\\Middleware.php", "source_location": "L53"}, {"caller_nid": "src_middleware_middleware_version", "callee": "file_exists", "is_member_call": false, "source_file": "C:\\Users\\Alex\\TraeCoder\\Maids.ng\\legacy-v1\\vendor\\inertiajs\\inertia-laravel\\src\\Middleware.php", "source_location": "L56"}, {"caller_nid": "src_middleware_middleware_version", "callee": "public_path", "is_member_call": false, "source_file": "C:\\Users\\Alex\\TraeCoder\\Maids.ng\\legacy-v1\\vendor\\inertiajs\\inertia-laravel\\src\\Middleware.php", "source_location": "L56"}, {"caller_nid": "src_middleware_middleware_version", "callee": "hash_file", "is_member_call": false, "source_file": "C:\\Users\\Alex\\TraeCoder\\Maids.ng\\legacy-v1\\vendor\\inertiajs\\inertia-laravel\\src\\Middleware.php", "source_location": "L57"}, {"caller_nid": "src_middleware_middleware_share", "callee": "Inertia", "is_member_call": false, "source_file": "C:\\Users\\Alex\\TraeCoder\\Maids.ng\\legacy-v1\\vendor\\inertiajs\\inertia-laravel\\src\\Middleware.php", "source_location": "L71"}, {"caller_nid": "src_middleware_middleware_handle", "callee": "Inertia", "is_member_call": false, "source_file": "C:\\Users\\Alex\\TraeCoder\\Maids.ng\\legacy-v1\\vendor\\inertiajs\\inertia-laravel\\src\\Middleware.php", "source_location": "L112"}, {"caller_nid": "src_middleware_middleware_handle", "callee": "Inertia", "is_member_call": false, "source_file": "C:\\Users\\Alex\\TraeCoder\\Maids.ng\\legacy-v1\\vendor\\inertiajs\\inertia-laravel\\src\\Middleware.php", "source_location": "L116"}, {"caller_nid": "src_middleware_middleware_handle", "callee": "Inertia", "is_member_call": false, "source_file": "C:\\Users\\Alex\\TraeCoder\\Maids.ng\\legacy-v1\\vendor\\inertiajs\\inertia-laravel\\src\\Middleware.php", "source_location": "L120"}, {"caller_nid": "src_middleware_middleware_handle", "callee": "Inertia", "is_member_call": false, "source_file": "C:\\Users\\Alex\\TraeCoder\\Maids.ng\\legacy-v1\\vendor\\inertiajs\\inertia-laravel\\src\\Middleware.php", "source_location": "L122"}, {"caller_nid": "src_middleware_middleware_handle", "callee": "Inertia", "is_member_call": false, "source_file": "C:\\Users\\Alex\\TraeCoder\\Maids.ng\\legacy-v1\\vendor\\inertiajs\\inertia-laravel\\src\\Middleware.php", "source_location": "L126"}, {"caller_nid": "src_middleware_middleware_handle", "callee": "Inertia", "is_member_call": false, "source_file": "C:\\Users\\Alex\\TraeCoder\\Maids.ng\\legacy-v1\\vendor\\inertiajs\\inertia-laravel\\src\\Middleware.php", "source_location": "L129"}, {"caller_nid": "src_middleware_middleware_handle", "callee": "app", "is_member_call": false, "source_file": "C:\\Users\\Alex\\TraeCoder\\Maids.ng\\legacy-v1\\vendor\\inertiajs\\inertia-laravel\\src\\Middleware.php", "source_location": "L132"}, {"caller_nid": "src_middleware_middleware_handle", "callee": "empty", "is_member_call": false, "source_file": "C:\\Users\\Alex\\TraeCoder\\Maids.ng\\legacy-v1\\vendor\\inertiajs\\inertia-laravel\\src\\Middleware.php", "source_location": "L134"}, {"caller_nid": "src_middleware_middleware_handle", "callee": "except", "is_member_call": true, "source_file": "C:\\Users\\Alex\\TraeCoder\\Maids.ng\\legacy-v1\\vendor\\inertiajs\\inertia-laravel\\src\\Middleware.php", "source_location": "L135"}, {"caller_nid": "src_middleware_middleware_handle", "callee": "$next", "is_member_call": false, "source_file": "C:\\Users\\Alex\\TraeCoder\\Maids.ng\\legacy-v1\\vendor\\inertiajs\\inertia-laravel\\src\\Middleware.php", "source_location": "L138"}, {"caller_nid": "src_middleware_middleware_handle", "callee": "set", "is_member_call": true, "source_file": "C:\\Users\\Alex\\TraeCoder\\Maids.ng\\legacy-v1\\vendor\\inertiajs\\inertia-laravel\\src\\Middleware.php", "source_location": "L139"}, {"caller_nid": "src_middleware_middleware_handle", "callee": "isRedirect", "is_member_call": true, "source_file": "C:\\Users\\Alex\\TraeCoder\\Maids.ng\\legacy-v1\\vendor\\inertiajs\\inertia-laravel\\src\\Middleware.php", "source_location": "L141"}, {"caller_nid": "src_middleware_middleware_handle", "callee": "header", "is_member_call": true, "source_file": "C:\\Users\\Alex\\TraeCoder\\Maids.ng\\legacy-v1\\vendor\\inertiajs\\inertia-laravel\\src\\Middleware.php", "source_location": "L145"}, {"caller_nid": "src_middleware_middleware_handle", "callee": "method", "is_member_call": true, "source_file": "C:\\Users\\Alex\\TraeCoder\\Maids.ng\\legacy-v1\\vendor\\inertiajs\\inertia-laravel\\src\\Middleware.php", "source_location": "L149"}, {"caller_nid": "src_middleware_middleware_handle", "callee": "header", "is_member_call": true, "source_file": "C:\\Users\\Alex\\TraeCoder\\Maids.ng\\legacy-v1\\vendor\\inertiajs\\inertia-laravel\\src\\Middleware.php", "source_location": "L149"}, {"caller_nid": "src_middleware_middleware_handle", "callee": "Inertia", "is_member_call": false, "source_file": "C:\\Users\\Alex\\TraeCoder\\Maids.ng\\legacy-v1\\vendor\\inertiajs\\inertia-laravel\\src\\Middleware.php", "source_location": "L149"}, {"caller_nid": "src_middleware_middleware_handle", "callee": "isOk", "is_member_call": true, "source_file": "C:\\Users\\Alex\\TraeCoder\\Maids.ng\\legacy-v1\\vendor\\inertiajs\\inertia-laravel\\src\\Middleware.php", "source_location": "L153"}, {"caller_nid": "src_middleware_middleware_handle", "callee": "empty", "is_member_call": false, "source_file": "C:\\Users\\Alex\\TraeCoder\\Maids.ng\\legacy-v1\\vendor\\inertiajs\\inertia-laravel\\src\\Middleware.php", "source_location": "L153"}, {"caller_nid": "src_middleware_middleware_handle", "callee": "getContent", "is_member_call": true, "source_file": "C:\\Users\\Alex\\TraeCoder\\Maids.ng\\legacy-v1\\vendor\\inertiajs\\inertia-laravel\\src\\Middleware.php", "source_location": "L153"}, {"caller_nid": "src_middleware_middleware_handle", "callee": "getStatusCode", "is_member_call": true, "source_file": "C:\\Users\\Alex\\TraeCoder\\Maids.ng\\legacy-v1\\vendor\\inertiajs\\inertia-laravel\\src\\Middleware.php", "source_location": "L157"}, {"caller_nid": "src_middleware_middleware_handle", "callee": "in_array", "is_member_call": false, "source_file": "C:\\Users\\Alex\\TraeCoder\\Maids.ng\\legacy-v1\\vendor\\inertiajs\\inertia-laravel\\src\\Middleware.php", "source_location": "L157"}, {"caller_nid": "src_middleware_middleware_handle", "callee": "method", "is_member_call": true, "source_file": "C:\\Users\\Alex\\TraeCoder\\Maids.ng\\legacy-v1\\vendor\\inertiajs\\inertia-laravel\\src\\Middleware.php", "source_location": "L157"}, {"caller_nid": "src_middleware_middleware_handle", "callee": "setStatusCode", "is_member_call": true, "source_file": "C:\\Users\\Alex\\TraeCoder\\Maids.ng\\legacy-v1\\vendor\\inertiajs\\inertia-laravel\\src\\Middleware.php", "source_location": "L158"}, {"caller_nid": "src_middleware_middleware_handle", "callee": "prefetch", "is_member_call": true, "source_file": "C:\\Users\\Alex\\TraeCoder\\Maids.ng\\legacy-v1\\vendor\\inertiajs\\inertia-laravel\\src\\Middleware.php", "source_location": "L161"}, {"caller_nid": "src_middleware_middleware_redirecthasfragment", "callee": "str_contains", "is_member_call": false, "source_file": "C:\\Users\\Alex\\TraeCoder\\Maids.ng\\legacy-v1\\vendor\\inertiajs\\inertia-laravel\\src\\Middleware.php", "source_location": "L173"}, {"caller_nid": "src_middleware_middleware_redirecthasfragment", "callee": "get", "is_member_call": true, "source_file": "C:\\Users\\Alex\\TraeCoder\\Maids.ng\\legacy-v1\\vendor\\inertiajs\\inertia-laravel\\src\\Middleware.php", "source_location": "L173"}, {"caller_nid": "src_middleware_middleware_reflash", "callee": "Inertia", "is_member_call": false, "source_file": "C:\\Users\\Alex\\TraeCoder\\Maids.ng\\legacy-v1\\vendor\\inertiajs\\inertia-laravel\\src\\Middleware.php", "source_location": "L181"}, {"caller_nid": "src_middleware_middleware_reflash", "callee": "flash", "is_member_call": true, "source_file": "C:\\Users\\Alex\\TraeCoder\\Maids.ng\\legacy-v1\\vendor\\inertiajs\\inertia-laravel\\src\\Middleware.php", "source_location": "L182"}, {"caller_nid": "src_middleware_middleware_reflash", "callee": "session", "is_member_call": true, "source_file": "C:\\Users\\Alex\\TraeCoder\\Maids.ng\\legacy-v1\\vendor\\inertiajs\\inertia-laravel\\src\\Middleware.php", "source_location": "L182"}, {"caller_nid": "src_middleware_middleware_onemptyresponse", "callee": "Redirect", "is_member_call": false, "source_file": "C:\\Users\\Alex\\TraeCoder\\Maids.ng\\legacy-v1\\vendor\\inertiajs\\inertia-laravel\\src\\Middleware.php", "source_location": "L191"}, {"caller_nid": "src_middleware_middleware_onredirectwithfragment", "callee": "response", "is_member_call": false, "source_file": "C:\\Users\\Alex\\TraeCoder\\Maids.ng\\legacy-v1\\vendor\\inertiajs\\inertia-laravel\\src\\Middleware.php", "source_location": "L199"}, {"caller_nid": "src_middleware_middleware_onredirectwithfragment", "callee": "get", "is_member_call": true, "source_file": "C:\\Users\\Alex\\TraeCoder\\Maids.ng\\legacy-v1\\vendor\\inertiajs\\inertia-laravel\\src\\Middleware.php", "source_location": "L200"}, {"caller_nid": "src_middleware_middleware_onversionchange", "callee": "hasSession", "is_member_call": true, "source_file": "C:\\Users\\Alex\\TraeCoder\\Maids.ng\\legacy-v1\\vendor\\inertiajs\\inertia-laravel\\src\\Middleware.php", "source_location": "L209"}, {"caller_nid": "src_middleware_middleware_onversionchange", "callee": "session", "is_member_call": true, "source_file": "C:\\Users\\Alex\\TraeCoder\\Maids.ng\\legacy-v1\\vendor\\inertiajs\\inertia-laravel\\src\\Middleware.php", "source_location": "L211"}, {"caller_nid": "src_middleware_middleware_onversionchange", "callee": "Inertia", "is_member_call": false, "source_file": "C:\\Users\\Alex\\TraeCoder\\Maids.ng\\legacy-v1\\vendor\\inertiajs\\inertia-laravel\\src\\Middleware.php", "source_location": "L215"}, {"caller_nid": "src_middleware_middleware_onversionchange", "callee": "fullUrl", "is_member_call": true, "source_file": "C:\\Users\\Alex\\TraeCoder\\Maids.ng\\legacy-v1\\vendor\\inertiajs\\inertia-laravel\\src\\Middleware.php", "source_location": "L215"}, {"caller_nid": "src_middleware_middleware_resolvevalidationerrors", "callee": "hasSession", "is_member_call": true, "source_file": "C:\\Users\\Alex\\TraeCoder\\Maids.ng\\legacy-v1\\vendor\\inertiajs\\inertia-laravel\\src\\Middleware.php", "source_location": "L225"}, {"caller_nid": "src_middleware_middleware_resolvevalidationerrors", "callee": "has", "is_member_call": true, "source_file": "C:\\Users\\Alex\\TraeCoder\\Maids.ng\\legacy-v1\\vendor\\inertiajs\\inertia-laravel\\src\\Middleware.php", "source_location": "L225"}, {"caller_nid": "src_middleware_middleware_resolvevalidationerrors", "callee": "session", "is_member_call": true, "source_file": "C:\\Users\\Alex\\TraeCoder\\Maids.ng\\legacy-v1\\vendor\\inertiajs\\inertia-laravel\\src\\Middleware.php", "source_location": "L225"}, {"caller_nid": "src_middleware_middleware_resolvevalidationerrors", "callee": "getBags", "is_member_call": true, "source_file": "C:\\Users\\Alex\\TraeCoder\\Maids.ng\\legacy-v1\\vendor\\inertiajs\\inertia-laravel\\src\\Middleware.php", "source_location": "L230"}, {"caller_nid": "src_middleware_middleware_resolvevalidationerrors", "callee": "get", "is_member_call": true, "source_file": "C:\\Users\\Alex\\TraeCoder\\Maids.ng\\legacy-v1\\vendor\\inertiajs\\inertia-laravel\\src\\Middleware.php", "source_location": "L230"}, {"caller_nid": "src_middleware_middleware_resolvevalidationerrors", "callee": "session", "is_member_call": true, "source_file": "C:\\Users\\Alex\\TraeCoder\\Maids.ng\\legacy-v1\\vendor\\inertiajs\\inertia-laravel\\src\\Middleware.php", "source_location": "L230"}, {"caller_nid": "src_middleware_middleware_resolvevalidationerrors", "callee": "pipe", "is_member_call": true, "source_file": "C:\\Users\\Alex\\TraeCoder\\Maids.ng\\legacy-v1\\vendor\\inertiajs\\inertia-laravel\\src\\Middleware.php", "source_location": "L232"}, {"caller_nid": "src_middleware_middleware_resolvevalidationerrors", "callee": "map", "is_member_call": true, "source_file": "C:\\Users\\Alex\\TraeCoder\\Maids.ng\\legacy-v1\\vendor\\inertiajs\\inertia-laravel\\src\\Middleware.php", "source_location": "L232"}, {"caller_nid": "src_middleware_middleware_resolvevalidationerrors", "callee": "collect", "is_member_call": false, "source_file": "C:\\Users\\Alex\\TraeCoder\\Maids.ng\\legacy-v1\\vendor\\inertiajs\\inertia-laravel\\src\\Middleware.php", "source_location": "L232"}, {"caller_nid": "src_middleware_middleware_resolvevalidationerrors", "callee": "toArray", "is_member_call": true, "source_file": "C:\\Users\\Alex\\TraeCoder\\Maids.ng\\legacy-v1\\vendor\\inertiajs\\inertia-laravel\\src\\Middleware.php", "source_location": "L233"}, {"caller_nid": "src_middleware_middleware_resolvevalidationerrors", "callee": "map", "is_member_call": true, "source_file": "C:\\Users\\Alex\\TraeCoder\\Maids.ng\\legacy-v1\\vendor\\inertiajs\\inertia-laravel\\src\\Middleware.php", "source_location": "L233"}, {"caller_nid": "src_middleware_middleware_resolvevalidationerrors", "callee": "collect", "is_member_call": false, "source_file": "C:\\Users\\Alex\\TraeCoder\\Maids.ng\\legacy-v1\\vendor\\inertiajs\\inertia-laravel\\src\\Middleware.php", "source_location": "L233"}, {"caller_nid": "src_middleware_middleware_resolvevalidationerrors", "callee": "messages", "is_member_call": true, "source_file": "C:\\Users\\Alex\\TraeCoder\\Maids.ng\\legacy-v1\\vendor\\inertiajs\\inertia-laravel\\src\\Middleware.php", "source_location": "L233"}, {"caller_nid": "src_middleware_middleware_resolvevalidationerrors", "callee": "has", "is_member_call": true, "source_file": "C:\\Users\\Alex\\TraeCoder\\Maids.ng\\legacy-v1\\vendor\\inertiajs\\inertia-laravel\\src\\Middleware.php", "source_location": "L237"}, {"caller_nid": "src_middleware_middleware_resolvevalidationerrors", "callee": "header", "is_member_call": true, "source_file": "C:\\Users\\Alex\\TraeCoder\\Maids.ng\\legacy-v1\\vendor\\inertiajs\\inertia-laravel\\src\\Middleware.php", "source_location": "L237"}, {"caller_nid": "src_middleware_middleware_resolvevalidationerrors", "callee": "header", "is_member_call": true, "source_file": "C:\\Users\\Alex\\TraeCoder\\Maids.ng\\legacy-v1\\vendor\\inertiajs\\inertia-laravel\\src\\Middleware.php", "source_location": "L238"}, {"caller_nid": "src_middleware_middleware_resolvevalidationerrors", "callee": "get", "is_member_call": true, "source_file": "C:\\Users\\Alex\\TraeCoder\\Maids.ng\\legacy-v1\\vendor\\inertiajs\\inertia-laravel\\src\\Middleware.php", "source_location": "L238"}, {"caller_nid": "src_middleware_middleware_resolvevalidationerrors", "callee": "has", "is_member_call": true, "source_file": "C:\\Users\\Alex\\TraeCoder\\Maids.ng\\legacy-v1\\vendor\\inertiajs\\inertia-laravel\\src\\Middleware.php", "source_location": "L241"}, {"caller_nid": "src_middleware_middleware_resolvevalidationerrors", "callee": "get", "is_member_call": true, "source_file": "C:\\Users\\Alex\\TraeCoder\\Maids.ng\\legacy-v1\\vendor\\inertiajs\\inertia-laravel\\src\\Middleware.php", "source_location": "L242"}, {"caller_nid": "src_middleware_middleware_resolvevalidationerrors", "callee": "toArray", "is_member_call": true, "source_file": "C:\\Users\\Alex\\TraeCoder\\Maids.ng\\legacy-v1\\vendor\\inertiajs\\inertia-laravel\\src\\Middleware.php", "source_location": "L245"}]}