{"nodes": [{"id": "c_users_alex_traecoder_maids_ng_legacy_v1_backend_vendor_ramsey_uuid_src_rfc4122_maxuuid_php", "label": "MaxUuid.php", "file_type": "code", "source_file": "C:\\Users\\Alex\\TraeCoder\\Maids.ng\\legacy-v1\\backend\\vendor\\ramsey\\uuid\\src\\Rfc4122\\MaxUuid.php", "source_location": "L1"}, {"id": "rfc4122_maxuuid_maxuuid", "label": "MaxUuid", "file_type": "code", "source_file": "C:\\Users\\Alex\\TraeCoder\\Maids.ng\\legacy-v1\\backend\\vendor\\ramsey\\uuid\\src\\Rfc4122\\MaxUuid.php", "source_location": "L26"}], "edges": [{"source": "c_users_alex_traecoder_maids_ng_legacy_v1_backend_vendor_ramsey_uuid_src_rfc4122_maxuuid_php", "target": "uuid", "relation": "imports", "confidence": "EXTRACTED", "source_file": "C:\\Users\\Alex\\TraeCoder\\Maids.ng\\legacy-v1\\backend\\vendor\\ramsey\\uuid\\src\\Rfc4122\\MaxUuid.php", "source_location": "L17", "weight": 1.0}, {"source": "c_users_alex_traecoder_maids_ng_legacy_v1_backend_vendor_ramsey_uuid_src_rfc4122_maxuuid_php", "target": "rfc4122_maxuuid_maxuuid", "relation": "contains", "confidence": "EXTRACTED", "source_file": "C:\\Users\\Alex\\TraeCoder\\Maids.ng\\legacy-v1\\backend\\vendor\\ramsey\\uuid\\src\\Rfc4122\\MaxUuid.php", "source_location": "L26", "weight": 1.0}], "raw_calls": []}