{"nodes": [{"id": "c_users_alex_traecoder_maids_ng_vendor_spatie_laravel_permission_src_commands_upgradeforteams_php", "label": "UpgradeForTeams.php", "file_type": "code", "source_file": "C:\\Users\\Alex\\TraeCoder\\Maids.ng\\vendor\\spatie\\laravel-permission\\src\\Commands\\UpgradeForTeams.php", "source_location": "L1"}, {"id": "commands_upgradeforteams_upgradeforteams", "label": "UpgradeForTeams", "file_type": "code", "source_file": "C:\\Users\\Alex\\TraeCoder\\Maids.ng\\vendor\\spatie\\laravel-permission\\src\\Commands\\UpgradeForTeams.php", "source_location": "L8"}, {"id": "commands_upgradeforteams_upgradeforteams_handle", "label": ".handle()", "file_type": "code", "source_file": "C:\\Users\\Alex\\TraeCoder\\Maids.ng\\vendor\\spatie\\laravel-permission\\src\\Commands\\UpgradeForTeams.php", "source_location": "L16"}, {"id": "commands_upgradeforteams_upgradeforteams_createmigration", "label": ".createMigration()", "file_type": "code", "source_file": "C:\\Users\\Alex\\TraeCoder\\Maids.ng\\vendor\\spatie\\laravel-permission\\src\\Commands\\UpgradeForTeams.php", "source_location": "L63"}, {"id": "commands_upgradeforteams_upgradeforteams_getexistingmigrationswarning", "label": ".getExistingMigrationsWarning()", "file_type": "code", "source_file": "C:\\Users\\Alex\\TraeCoder\\Maids.ng\\vendor\\spatie\\laravel-permission\\src\\Commands\\UpgradeForTeams.php", "source_location": "L83"}, {"id": "commands_upgradeforteams_upgradeforteams_alreadyexistingmigrations", "label": ".alreadyExistingMigrations()", "file_type": "code", "source_file": "C:\\Users\\Alex\\TraeCoder\\Maids.ng\\vendor\\spatie\\laravel-permission\\src\\Commands\\UpgradeForTeams.php", "source_location": "L100"}, {"id": "commands_upgradeforteams_upgradeforteams_getmigrationpath", "label": ".getMigrationPath()", "file_type": "code", "source_file": "C:\\Users\\Alex\\TraeCoder\\Maids.ng\\vendor\\spatie\\laravel-permission\\src\\Commands\\UpgradeForTeams.php", "source_location": "L116"}], "edges": [{"source": "c_users_alex_traecoder_maids_ng_vendor_spatie_laravel_permission_src_commands_upgradeforteams_php", "target": "command", "relation": "imports", "confidence": "EXTRACTED", "source_file": "C:\\Users\\Alex\\TraeCoder\\Maids.ng\\vendor\\spatie\\laravel-permission\\src\\Commands\\UpgradeForTeams.php", "source_location": "L5", "weight": 1.0}, {"source": "c_users_alex_traecoder_maids_ng_vendor_spatie_laravel_permission_src_commands_upgradeforteams_php", "target": "config", "relation": "imports", "confidence": "EXTRACTED", "source_file": "C:\\Users\\Alex\\TraeCoder\\Maids.ng\\vendor\\spatie\\laravel-permission\\src\\Commands\\UpgradeForTeams.php", "source_location": "L6", "weight": 1.0}, {"source": "c_users_alex_traecoder_maids_ng_vendor_spatie_laravel_permission_src_commands_upgradeforteams_php", "target": "commands_upgradeforteams_upgradeforteams", "relation": "contains", "confidence": "EXTRACTED", "source_file": "C:\\Users\\Alex\\TraeCoder\\Maids.ng\\vendor\\spatie\\laravel-permission\\src\\Commands\\UpgradeForTeams.php", "source_location": "L8", "weight": 1.0}, {"source": "commands_upgradeforteams_upgradeforteams", "target": "commands_upgradeforteams_upgradeforteams_handle", "relation": "method", "confidence": "EXTRACTED", "source_file": "C:\\Users\\Alex\\TraeCoder\\Maids.ng\\vendor\\spatie\\laravel-permission\\src\\Commands\\UpgradeForTeams.php", "source_location": "L16", "weight": 1.0}, {"source": "commands_upgradeforteams_upgradeforteams", "target": "commands_upgradeforteams_upgradeforteams_createmigration", "relation": "method", "confidence": "EXTRACTED", "source_file": "C:\\Users\\Alex\\TraeCoder\\Maids.ng\\vendor\\spatie\\laravel-permission\\src\\Commands\\UpgradeForTeams.php", "source_location": "L63", "weight": 1.0}, {"source": "commands_upgradeforteams_upgradeforteams", "target": "commands_upgradeforteams_upgradeforteams_getexistingmigrationswarning", "relation": "method", "confidence": "EXTRACTED", "source_file": "C:\\Users\\Alex\\TraeCoder\\Maids.ng\\vendor\\spatie\\laravel-permission\\src\\Commands\\UpgradeForTeams.php", "source_location": "L83", "weight": 1.0}, {"source": "commands_upgradeforteams_upgradeforteams", "target": "commands_upgradeforteams_upgradeforteams_alreadyexistingmigrations", "relation": "method", "confidence": "EXTRACTED", "source_file": "C:\\Users\\Alex\\TraeCoder\\Maids.ng\\vendor\\spatie\\laravel-permission\\src\\Commands\\UpgradeForTeams.php", "source_location": "L100", "weight": 1.0}, {"source": "commands_upgradeforteams_upgradeforteams", "target": "commands_upgradeforteams_upgradeforteams_getmigrationpath", "relation": "method", "confidence": "EXTRACTED", "source_file": "C:\\Users\\Alex\\TraeCoder\\Maids.ng\\vendor\\spatie\\laravel-permission\\src\\Commands\\UpgradeForTeams.php", "source_location": "L116", "weight": 1.0}, {"source": "commands_upgradeforteams_upgradeforteams_handle", "target": "commands_upgradeforteams_upgradeforteams_alreadyexistingmigrations", "relation": "calls", "confidence": "EXTRACTED", "source_file": "C:\\Users\\Alex\\TraeCoder\\Maids.ng\\vendor\\spatie\\laravel-permission\\src\\Commands\\UpgradeForTeams.php", "source_location": "L28", "weight": 1.0}, {"source": "commands_upgradeforteams_upgradeforteams_handle", "target": "commands_upgradeforteams_upgradeforteams_getexistingmigrationswarning", "relation": "calls", "confidence": "EXTRACTED", "source_file": "C:\\Users\\Alex\\TraeCoder\\Maids.ng\\vendor\\spatie\\laravel-permission\\src\\Commands\\UpgradeForTeams.php", "source_location": "L33", "weight": 1.0}, {"source": "commands_upgradeforteams_upgradeforteams_handle", "target": "commands_upgradeforteams_upgradeforteams_createmigration", "relation": "calls", "confidence": "EXTRACTED", "source_file": "C:\\Users\\Alex\\TraeCoder\\Maids.ng\\vendor\\spatie\\laravel-permission\\src\\Commands\\UpgradeForTeams.php", "source_location": "L46", "weight": 1.0}, {"source": "commands_upgradeforteams_upgradeforteams_createmigration", "target": "commands_upgradeforteams_upgradeforteams_getmigrationpath", "relation": "calls", "confidence": "EXTRACTED", "source_file": "C:\\Users\\Alex\\TraeCoder\\Maids.ng\\vendor\\spatie\\laravel-permission\\src\\Commands\\UpgradeForTeams.php", "source_location": "L67", "weight": 1.0}, {"source": "commands_upgradeforteams_upgradeforteams_alreadyexistingmigrations", "target": "commands_upgradeforteams_upgradeforteams_getmigrationpath", "relation": "calls", "confidence": "EXTRACTED", "source_file": "C:\\Users\\Alex\\TraeCoder\\Maids.ng\\vendor\\spatie\\laravel-permission\\src\\Commands\\UpgradeForTeams.php", "source_location": "L102", "weight": 1.0}], "raw_calls": [{"caller_nid": "commands_upgradeforteams_upgradeforteams_handle", "callee": "Config", "is_member_call": false, "source_file": "C:\\Users\\Alex\\TraeCoder\\Maids.ng\\vendor\\spatie\\laravel-permission\\src\\Commands\\UpgradeForTeams.php", "source_location": "L18"}, {"caller_nid": "commands_upgradeforteams_upgradeforteams_handle", "callee": "error", "is_member_call": true, "source_file": "C:\\Users\\Alex\\TraeCoder\\Maids.ng\\vendor\\spatie\\laravel-permission\\src\\Commands\\UpgradeForTeams.php", "source_location": "L19"}, {"caller_nid": "commands_upgradeforteams_upgradeforteams_handle", "callee": "warn", "is_member_call": true, "source_file": "C:\\Users\\Alex\\TraeCoder\\Maids.ng\\vendor\\spatie\\laravel-permission\\src\\Commands\\UpgradeForTeams.php", "source_location": "L20"}, {"caller_nid": "commands_upgradeforteams_upgradeforteams_handle", "callee": "line", "is_member_call": true, "source_file": "C:\\Users\\Alex\\TraeCoder\\Maids.ng\\vendor\\spatie\\laravel-permission\\src\\Commands\\UpgradeForTeams.php", "source_location": "L25"}, {"caller_nid": "commands_upgradeforteams_upgradeforteams_handle", "callee": "info", "is_member_call": true, "source_file": "C:\\Users\\Alex\\TraeCoder\\Maids.ng\\vendor\\spatie\\laravel-permission\\src\\Commands\\UpgradeForTeams.php", "source_location": "L26"}, {"caller_nid": "commands_upgradeforteams_upgradeforteams_handle", "callee": "line", "is_member_call": true, "source_file": "C:\\Users\\Alex\\TraeCoder\\Maids.ng\\vendor\\spatie\\laravel-permission\\src\\Commands\\UpgradeForTeams.php", "source_location": "L31"}, {"caller_nid": "commands_upgradeforteams_upgradeforteams_handle", "callee": "warn", "is_member_call": true, "source_file": "C:\\Users\\Alex\\TraeCoder\\Maids.ng\\vendor\\spatie\\laravel-permission\\src\\Commands\\UpgradeForTeams.php", "source_location": "L33"}, {"caller_nid": "commands_upgradeforteams_upgradeforteams_handle", "callee": "line", "is_member_call": true, "source_file": "C:\\Users\\Alex\\TraeCoder\\Maids.ng\\vendor\\spatie\\laravel-permission\\src\\Commands\\UpgradeForTeams.php", "source_location": "L36"}, {"caller_nid": "commands_upgradeforteams_upgradeforteams_handle", "callee": "confirm", "is_member_call": true, "source_file": "C:\\Users\\Alex\\TraeCoder\\Maids.ng\\vendor\\spatie\\laravel-permission\\src\\Commands\\UpgradeForTeams.php", "source_location": "L38"}, {"caller_nid": "commands_upgradeforteams_upgradeforteams_handle", "callee": "line", "is_member_call": true, "source_file": "C:\\Users\\Alex\\TraeCoder\\Maids.ng\\vendor\\spatie\\laravel-permission\\src\\Commands\\UpgradeForTeams.php", "source_location": "L42"}, {"caller_nid": "commands_upgradeforteams_upgradeforteams_handle", "callee": "line", "is_member_call": true, "source_file": "C:\\Users\\Alex\\TraeCoder\\Maids.ng\\vendor\\spatie\\laravel-permission\\src\\Commands\\UpgradeForTeams.php", "source_location": "L44"}, {"caller_nid": "commands_upgradeforteams_upgradeforteams_handle", "callee": "info", "is_member_call": true, "source_file": "C:\\Users\\Alex\\TraeCoder\\Maids.ng\\vendor\\spatie\\laravel-permission\\src\\Commands\\UpgradeForTeams.php", "source_location": "L47"}, {"caller_nid": "commands_upgradeforteams_upgradeforteams_handle", "callee": "error", "is_member_call": true, "source_file": "C:\\Users\\Alex\\TraeCoder\\Maids.ng\\vendor\\spatie\\laravel-permission\\src\\Commands\\UpgradeForTeams.php", "source_location": "L49"}, {"caller_nid": "commands_upgradeforteams_upgradeforteams_handle", "callee": "line", "is_member_call": true, "source_file": "C:\\Users\\Alex\\TraeCoder\\Maids.ng\\vendor\\spatie\\laravel-permission\\src\\Commands\\UpgradeForTeams.php", "source_location": "L55"}, {"caller_nid": "commands_upgradeforteams_upgradeforteams_createmigration", "callee": "copy", "is_member_call": false, "source_file": "C:\\Users\\Alex\\TraeCoder\\Maids.ng\\vendor\\spatie\\laravel-permission\\src\\Commands\\UpgradeForTeams.php", "source_location": "L67"}, {"caller_nid": "commands_upgradeforteams_upgradeforteams_createmigration", "callee": "error", "is_member_call": true, "source_file": "C:\\Users\\Alex\\TraeCoder\\Maids.ng\\vendor\\spatie\\laravel-permission\\src\\Commands\\UpgradeForTeams.php", "source_location": "L71"}, {"caller_nid": "commands_upgradeforteams_upgradeforteams_createmigration", "callee": "getMessage", "is_member_call": true, "source_file": "C:\\Users\\Alex\\TraeCoder\\Maids.ng\\vendor\\spatie\\laravel-permission\\src\\Commands\\UpgradeForTeams.php", "source_location": "L71"}, {"caller_nid": "commands_upgradeforteams_upgradeforteams_getexistingmigrationswarning", "callee": "count", "is_member_call": false, "source_file": "C:\\Users\\Alex\\TraeCoder\\Maids.ng\\vendor\\spatie\\laravel-permission\\src\\Commands\\UpgradeForTeams.php", "source_location": "L85"}, {"caller_nid": "commands_upgradeforteams_upgradeforteams_getexistingmigrationswarning", "callee": "array_reduce", "is_member_call": false, "source_file": "C:\\Users\\Alex\\TraeCoder\\Maids.ng\\vendor\\spatie\\laravel-permission\\src\\Commands\\UpgradeForTeams.php", "source_location": "L91"}, {"caller_nid": "commands_upgradeforteams_upgradeforteams_alreadyexistingmigrations", "callee": "glob", "is_member_call": false, "source_file": "C:\\Users\\Alex\\TraeCoder\\Maids.ng\\vendor\\spatie\\laravel-permission\\src\\Commands\\UpgradeForTeams.php", "source_location": "L102"}, {"caller_nid": "commands_upgradeforteams_upgradeforteams_alreadyexistingmigrations", "callee": "array_map", "is_member_call": false, "source_file": "C:\\Users\\Alex\\TraeCoder\\Maids.ng\\vendor\\spatie\\laravel-permission\\src\\Commands\\UpgradeForTeams.php", "source_location": "L104"}, {"caller_nid": "commands_upgradeforteams_upgradeforteams_alreadyexistingmigrations", "callee": "basename", "is_member_call": false, "source_file": "C:\\Users\\Alex\\TraeCoder\\Maids.ng\\vendor\\spatie\\laravel-permission\\src\\Commands\\UpgradeForTeams.php", "source_location": "L104"}, {"caller_nid": "commands_upgradeforteams_upgradeforteams_getmigrationpath", "callee": "date", "is_member_call": false, "source_file": "C:\\Users\\Alex\\TraeCoder\\Maids.ng\\vendor\\spatie\\laravel-permission\\src\\Commands\\UpgradeForTeams.php", "source_location": "L118"}, {"caller_nid": "commands_upgradeforteams_upgradeforteams_getmigrationpath", "callee": "database_path", "is_member_call": false, "source_file": "C:\\Users\\Alex\\TraeCoder\\Maids.ng\\vendor\\spatie\\laravel-permission\\src\\Commands\\UpgradeForTeams.php", "source_location": "L120"}]}